{
    "ID": "i5h5id0aunjdm1lk5wsm",
    "ProcessName": "gcsum",
    "Command": "awk '{ SUM += $1 } END { print SUM }' ../gccounts.txt \u003e gccounts.txt.sum",
    "Params": {},
    "Tags": {},
    "StartTime": "2023-02-25T13:00:21.850627724Z",
    "FinishTime": "2023-02-25T13:00:21.852713143Z",
    "ExecTimeNS": 2085418,
    "OutFiles": {
        "sum": "gccounts.txt.sum"
    },
    "Upstream": {
        "gccounts.txt": {
            "ID": "bb8211z21zt2aeygf1gt",
            "ProcessName": "",
            "Command": "",
            "Params": {},
            "Tags": {},
            "StartTime": "0001-01-01T00:00:00Z",
            "FinishTime": "0001-01-01T00:00:00Z",
            "ExecTimeNS": -1,
            "OutFiles": {},
            "Upstream": {}
        }
    }
}