{
    "ID": "3pb5zkw6bxbucogmwwv8",
    "ProcessName": "gcratio",
    "Command": "gc=$(cat ../gccounts.txt.sum); at=$(cat ../atcounts.txt.sum); calc \"$gc/($gc+$at)\" \u003e gcratio.txt",
    "Params": {},
    "Tags": {},
    "StartTime": "2023-03-13T02:26:09.05394539Z",
    "FinishTime": "2023-03-13T02:26:09.057981439Z",
    "ExecTimeNS": 4036039,
    "OutFiles": {
        "gcratio": "gcratio.txt"
    },
    "Upstream": {
        "atcounts.txt.sum": {
            "ID": "1je9py38xypl74z1r0jf",
            "ProcessName": "atsum",
            "Command": "awk '{ SUM += $1 } END { print SUM }' ../atcounts.txt \u003e atcounts.txt.sum",
            "Params": {},
            "Tags": {},
            "StartTime": "2023-03-13T02:26:09.047645885Z",
            "FinishTime": "2023-03-13T02:26:09.051418913Z",
            "ExecTimeNS": 3773008,
            "OutFiles": {
                "sum": "atcounts.txt.sum"
            },
            "Upstream": {
                "atcounts.txt": {
                    "ID": "vgo7ulqm0v39aadmqfsb",
                    "ProcessName": "",
                    "Command": "",
                    "Params": {},
                    "Tags": {},
                    "StartTime": "0001-01-01T00:00:00Z",
                    "FinishTime": "0001-01-01T00:00:00Z",
                    "ExecTimeNS": -1,
                    "OutFiles": {},
                    "Upstream": {}
                }
            }
        },
        "gccounts.txt.sum": {
            "ID": "0tl2vyidqrparzj1fahq",
            "ProcessName": "gcsum",
            "Command": "awk '{ SUM += $1 } END { print SUM }' ../gccounts.txt \u003e gccounts.txt.sum",
            "Params": {},
            "Tags": {},
            "StartTime": "2023-03-13T02:26:09.049854197Z",
            "FinishTime": "2023-03-13T02:26:09.052969373Z",
            "ExecTimeNS": 3115166,
            "OutFiles": {
                "sum": "gccounts.txt.sum"
            },
            "Upstream": {
                "gccounts.txt": {
                    "ID": "4py1pqpc9u3ia620hu9a",
                    "ProcessName": "",
                    "Command": "",
                    "Params": {},
                    "Tags": {},
                    "StartTime": "0001-01-01T00:00:00Z",
                    "FinishTime": "0001-01-01T00:00:00Z",
                    "ExecTimeNS": -1,
                    "OutFiles": {},
                    "Upstream": {}
                }
            }
        }
    }
}