{
    "ID": "0sxx2v7u1n51o24c9ppm",
    "ProcessName": "atsum",
    "Command": "awk '{ SUM += $1 } END { print SUM }' ../atcounts.txt \u003e atcounts.txt.sum",
    "Params": {},
    "Tags": {},
    "StartTime": "2023-03-13T02:26:24.368946745Z",
    "FinishTime": "2023-03-13T02:26:24.372061898Z",
    "ExecTimeNS": 3115153,
    "OutFiles": {
        "sum": "atcounts.txt.sum"
    },
    "Upstream": {
        "atcounts.txt": {
            "ID": "egej6ekqtkc7x0zjvjz1",
            "ProcessName": "",
            "Command": "",
            "Params": {},
            "Tags": {},
            "StartTime": "0001-01-01T00:00:00Z",
            "FinishTime": "0001-01-01T00:00:00Z",
            "ExecTimeNS": -1,
            "OutFiles": {},
            "Upstream": {}
        }
    }
}