{
    "ID": "47c8drnlwf1aebpun9tm",
    "ProcessName": "gcsum",
    "Command": "awk '{ SUM += $1 } END { print SUM }' ../gccounts.txt \u003e gccounts.txt.sum",
    "Params": {},
    "Tags": {},
    "StartTime": "2023-03-13T02:27:17.285360333Z",
    "FinishTime": "2023-03-13T02:27:17.288247105Z",
    "ExecTimeNS": 2886763,
    "OutFiles": {
        "sum": "gccounts.txt.sum"
    },
    "Upstream": {
        "gccounts.txt": {
            "ID": "gygst34aflkhrhgpc432",
            "ProcessName": "",
            "Command": "",
            "Params": {},
            "Tags": {},
            "StartTime": "0001-01-01T00:00:00Z",
            "FinishTime": "0001-01-01T00:00:00Z",
            "ExecTimeNS": -1,
            "OutFiles": {},
            "Upstream": {}
        }
    }
}