{
    "ID": "o23259rvswgg217nafmn",
    "ProcessName": "atcount2",
    "Command": "sed -n 1,$(cat ../count2.txt)p /home/ubuntu/projects/causality-fbp/scipipe-demo/dna_segment_2 | fold -w 1 | grep '[AT]' | wc -l | awk '{ print $1 }' \u003e chry.fa.atcnt2",
    "Params": {},
    "Tags": {},
    "StartTime": "2023-03-13T02:26:54.537249229Z",
    "FinishTime": "2023-03-13T02:26:54.541234885Z",
    "ExecTimeNS": 3985667,
    "OutFiles": {
        "atcount": "chry.fa.atcnt2"
    },
    "Upstream": {
        "count2.txt": {
            "ID": "oopsb6n3nztauhl9ugbp",
            "ProcessName": "count2",
            "Command": "echo 89 \u003e count2.txt",
            "Params": {},
            "Tags": {},
            "StartTime": "2023-03-13T02:26:54.535663832Z",
            "FinishTime": "2023-03-13T02:26:54.536755714Z",
            "ExecTimeNS": 1091883,
            "OutFiles": {
                "count": "count2.txt"
            },
            "Upstream": {}
        }
    }
}