{
    "ID": "n8w3j76o96ok234wp4ky",
    "ProcessName": "gcsum",
    "Command": "awk '{ SUM += $1 } END { print SUM }' ../gccounts.txt \u003e gccounts.txt.sum",
    "Params": {},
    "Tags": {},
    "StartTime": "2023-02-25T12:57:43.669126242Z",
    "FinishTime": "2023-02-25T12:57:43.67168076Z",
    "ExecTimeNS": 2554518,
    "OutFiles": {
        "sum": "gccounts.txt.sum"
    },
    "Upstream": {
        "gccounts.txt": {
            "ID": "lk1lza957mtcpe83u49w",
            "ProcessName": "",
            "Command": "",
            "Params": {},
            "Tags": {},
            "StartTime": "0001-01-01T00:00:00Z",
            "FinishTime": "0001-01-01T00:00:00Z",
            "ExecTimeNS": -1,
            "OutFiles": {},
            "Upstream": {}
        }
    }
}