{
    "ID": "lsyc4voox1k3ajop7717",
    "ProcessName": "atcount2",
    "Command": "sed -n 1,$(cat ../count2.txt)p /home/ubuntu/projects/causality-fbp/scipipe-demo/dna_segment_2 | fold -w 1 | grep '[AT]' | wc -l | awk '{ print $1 }' \u003e chry.fa.atcnt2",
    "Params": {},
    "Tags": {},
    "StartTime": "2023-03-13T02:26:34.583554767Z",
    "FinishTime": "2023-03-13T02:26:34.58911496Z",
    "ExecTimeNS": 5560194,
    "OutFiles": {
        "atcount": "chry.fa.atcnt2"
    },
    "Upstream": {
        "count2.txt": {
            "ID": "20xgjh48o2rv8a55eob0",
            "ProcessName": "count2",
            "Command": "echo 38 \u003e count2.txt",
            "Params": {},
            "Tags": {},
            "StartTime": "2023-03-13T02:26:34.581083606Z",
            "FinishTime": "2023-03-13T02:26:34.582851509Z",
            "ExecTimeNS": 1767883,
            "OutFiles": {
                "count": "count2.txt"
            },
            "Upstream": {}
        }
    }
}