{
    "ID": "p3ldp4t5ybrup91yrdhk",
    "ProcessName": "gccount2",
    "Command": "sed -n 1,$(cat ../count2.txt)p /home/ubuntu/projects/causality-fbp/scipipe-demo/dna_segment_2 | fold -w 1 | grep '[GC]' | wc -l | awk '{ print $1 }' \u003e chry.fa.gccnt2",
    "Params": {},
    "Tags": {},
    "StartTime": "2023-03-13T02:24:12.090991584Z",
    "FinishTime": "2023-03-13T02:24:12.096570846Z",
    "ExecTimeNS": 5579242,
    "OutFiles": {
        "gccount": "chry.fa.gccnt2"
    },
    "Upstream": {
        "count2.txt": {
            "ID": "0oiw88e83oklb82forsd",
            "ProcessName": "count2",
            "Command": "echo 32 \u003e count2.txt",
            "Params": {},
            "Tags": {},
            "StartTime": "2023-03-13T02:24:12.089404525Z",
            "FinishTime": "2023-03-13T02:24:12.090438903Z",
            "ExecTimeNS": 1034368,
            "OutFiles": {
                "count": "count2.txt"
            },
            "Upstream": {}
        }
    }
}