{
    "ID": "cklvua3ur6bq55nsw0x0",
    "ProcessName": "gcratio",
    "Command": "gc=$(cat ../gccounts.txt.sum); at=$(cat ../atcounts.txt.sum); calc \"$gc/($gc+$at)\" \u003e gcratio.txt",
    "Params": {},
    "Tags": {},
    "StartTime": "2023-02-26T22:18:26.261823707Z",
    "FinishTime": "2023-02-26T22:18:26.265053741Z",
    "ExecTimeNS": 3230024,
    "OutFiles": {
        "gcratio": "gcratio.txt"
    },
    "Upstream": {
        "atcounts.txt.sum": {
            "ID": "5lje6pa57otikz5wp2f3",
            "ProcessName": "atsum",
            "Command": "awk '{ SUM += $1 } END { print SUM }' ../atcounts.txt \u003e atcounts.txt.sum",
            "Params": {},
            "Tags": {},
            "StartTime": "2023-02-26T22:18:26.25874336Z",
            "FinishTime": "2023-02-26T22:18:26.261179935Z",
            "ExecTimeNS": 2436565,
            "OutFiles": {
                "sum": "atcounts.txt.sum"
            },
            "Upstream": {
                "atcounts.txt": {
                    "ID": "j4jp6hmz5dioc87f0zpe",
                    "ProcessName": "",
                    "Command": "",
                    "Params": {},
                    "Tags": {},
                    "StartTime": "0001-01-01T00:00:00Z",
                    "FinishTime": "0001-01-01T00:00:00Z",
                    "ExecTimeNS": -1,
                    "OutFiles": {},
                    "Upstream": {}
                }
            }
        },
        "gccounts.txt.sum": {
            "ID": "r54roqrt1mw98otp918y",
            "ProcessName": "gcsum",
            "Command": "awk '{ SUM += $1 } END { print SUM }' ../gccounts.txt \u003e gccounts.txt.sum",
            "Params": {},
            "Tags": {},
            "StartTime": "2023-02-26T22:18:26.258663701Z",
            "FinishTime": "2023-02-26T22:18:26.261027658Z",
            "ExecTimeNS": 2363947,
            "OutFiles": {
                "sum": "gccounts.txt.sum"
            },
            "Upstream": {
                "gccounts.txt": {
                    "ID": "76oiac8u1rf16c79g882",
                    "ProcessName": "",
                    "Command": "",
                    "Params": {},
                    "Tags": {},
                    "StartTime": "0001-01-01T00:00:00Z",
                    "FinishTime": "0001-01-01T00:00:00Z",
                    "ExecTimeNS": -1,
                    "OutFiles": {},
                    "Upstream": {}
                }
            }
        }
    }
}