{
    "ID": "ihkyzn80wi94xc7y04fz",
    "ProcessName": "atcount2",
    "Command": "sed -n 1,$(cat ../count2.txt)p /home/ubuntu/projects/causality-fbp/scipipe-demo/dna_segment_2 | fold -w 1 | grep '[AT]' | wc -l | awk '{ print $1 }' \u003e chry.fa.atcnt2",
    "Params": {},
    "Tags": {},
    "StartTime": "2023-03-13T02:27:43.470182047Z",
    "FinishTime": "2023-03-13T02:27:43.473815617Z",
    "ExecTimeNS": 3633580,
    "OutFiles": {
        "atcount": "chry.fa.atcnt2"
    },
    "Upstream": {
        "count2.txt": {
            "ID": "llxmeth4k95y47ffzpk7",
            "ProcessName": "count2",
            "Command": "echo 81 \u003e count2.txt",
            "Params": {},
            "Tags": {},
            "StartTime": "2023-03-13T02:27:43.468747057Z",
            "FinishTime": "2023-03-13T02:27:43.469761347Z",
            "ExecTimeNS": 1014300,
            "OutFiles": {
                "count": "count2.txt"
            },
            "Upstream": {}
        }
    }
}