{
    "ID": "7ecpjggn2aidz7ohoare",
    "ProcessName": "gccount1",
    "Command": "sed -n 1,$(cat ../count1.txt)p /home/ubuntu/projects/causality-fbp/scipipe-demo/dna_segment_1 | fold -w 1 | grep '[GC]' | wc -l | awk '{ print $1 }' \u003e chry.fa.gccnt1",
    "Params": {},
    "Tags": {},
    "StartTime": "2023-03-13T02:26:32.867969305Z",
    "FinishTime": "2023-03-13T02:26:32.872927027Z",
    "ExecTimeNS": 4957732,
    "OutFiles": {
        "gccount": "chry.fa.gccnt1"
    },
    "Upstream": {
        "count1.txt": {
            "ID": "bnteyuar5c9g5a4ncgj5",
            "ProcessName": "count1",
            "Command": "echo 84 \u003e count1.txt",
            "Params": {},
            "Tags": {},
            "StartTime": "2023-03-13T02:26:32.866107202Z",
            "FinishTime": "2023-03-13T02:26:32.867328552Z",
            "ExecTimeNS": 1221340,
            "OutFiles": {
                "count": "count1.txt"
            },
            "Upstream": {}
        }
    }
}