{
    "ID": "hhifkzfluykwgy6d0ti9",
    "ProcessName": "gccount2",
    "Command": "sed -n 1,$(cat ../count2.txt)p /home/ubuntu/projects/causality-fbp/scipipe-demo/dna_segment_2 | fold -w 1 | grep '[GC]' | wc -l | awk '{ print $1 }' \u003e chry.fa.gccnt2",
    "Params": {},
    "Tags": {},
    "StartTime": "2023-03-13T02:26:17.402093945Z",
    "FinishTime": "2023-03-13T02:26:17.40694503Z",
    "ExecTimeNS": 4851095,
    "OutFiles": {
        "gccount": "chry.fa.gccnt2"
    },
    "Upstream": {
        "count2.txt": {
            "ID": "dh3uki9eav33ui3c0k76",
            "ProcessName": "count2",
            "Command": "echo 73 \u003e count2.txt",
            "Params": {},
            "Tags": {},
            "StartTime": "2023-03-13T02:26:17.399432241Z",
            "FinishTime": "2023-03-13T02:26:17.401056992Z",
            "ExecTimeNS": 1624731,
            "OutFiles": {
                "count": "count2.txt"
            },
            "Upstream": {}
        }
    }
}