{
    "ID": "pv9oo6uwr3zmjb9z4nt6",
    "ProcessName": "gcratio",
    "Command": "gc=$(cat ../gccounts.txt.sum); at=$(cat ../atcounts.txt.sum); calc \"$gc/($gc+$at)\" \u003e gcratio.txt",
    "Params": {},
    "Tags": {},
    "StartTime": "2023-02-25T12:56:56.200585077Z",
    "FinishTime": "2023-02-25T12:56:56.203455972Z",
    "ExecTimeNS": 2870905,
    "OutFiles": {
        "gcratio": "gcratio.txt"
    },
    "Upstream": {
        "atcounts.txt.sum": {
            "ID": "2g2r10l552vr5meb1dxa",
            "ProcessName": "atsum",
            "Command": "awk '{ SUM += $1 } END { print SUM }' ../atcounts.txt \u003e atcounts.txt.sum",
            "Params": {},
            "Tags": {},
            "StartTime": "2023-02-25T12:56:56.197068163Z",
            "FinishTime": "2023-02-25T12:56:56.200173296Z",
            "ExecTimeNS": 3105133,
            "OutFiles": {
                "sum": "atcounts.txt.sum"
            },
            "Upstream": {
                "atcounts.txt": {
                    "ID": "qlm3r4e1f3r29opjk5nt",
                    "ProcessName": "",
                    "Command": "",
                    "Params": {},
                    "Tags": {},
                    "StartTime": "0001-01-01T00:00:00Z",
                    "FinishTime": "0001-01-01T00:00:00Z",
                    "ExecTimeNS": -1,
                    "OutFiles": {},
                    "Upstream": {}
                }
            }
        },
        "gccounts.txt.sum": {
            "ID": "epn6t5o2bm0zr54tpoxl",
            "ProcessName": "gcsum",
            "Command": "awk '{ SUM += $1 } END { print SUM }' ../gccounts.txt \u003e gccounts.txt.sum",
            "Params": {},
            "Tags": {},
            "StartTime": "2023-02-25T12:56:56.197749319Z",
            "FinishTime": "2023-02-25T12:56:56.200062569Z",
            "ExecTimeNS": 2313250,
            "OutFiles": {
                "sum": "gccounts.txt.sum"
            },
            "Upstream": {
                "gccounts.txt": {
                    "ID": "944wq16x8czk5jm7s8j2",
                    "ProcessName": "",
                    "Command": "",
                    "Params": {},
                    "Tags": {},
                    "StartTime": "0001-01-01T00:00:00Z",
                    "FinishTime": "0001-01-01T00:00:00Z",
                    "ExecTimeNS": -1,
                    "OutFiles": {},
                    "Upstream": {}
                }
            }
        }
    }
}