{
    "ID": "sps3ozjm46s7p55fpaeu",
    "ProcessName": "atsum",
    "Command": "awk '{ SUM += $1 } END { print SUM }' ../atcounts.txt \u003e atcounts.txt.sum",
    "Params": {},
    "Tags": {},
    "StartTime": "2023-03-13T02:21:49.317122135Z",
    "FinishTime": "2023-03-13T02:21:49.318603653Z",
    "ExecTimeNS": 1481529,
    "OutFiles": {
        "sum": "atcounts.txt.sum"
    },
    "Upstream": {
        "atcounts.txt": {
            "ID": "80lapz9py8cmanxnhz6b",
            "ProcessName": "",
            "Command": "",
            "Params": {},
            "Tags": {},
            "StartTime": "0001-01-01T00:00:00Z",
            "FinishTime": "0001-01-01T00:00:00Z",
            "ExecTimeNS": -1,
            "OutFiles": {},
            "Upstream": {}
        }
    }
}