{
    "ID": "quaa05oael9r8w7vqt1m",
    "ProcessName": "atsum",
    "Command": "awk '{ SUM += $1 } END { print SUM }' ../atcounts.txt \u003e atcounts.txt.sum",
    "Params": {},
    "Tags": {},
    "StartTime": "2023-03-13T02:27:34.410932474Z",
    "FinishTime": "2023-03-13T02:27:34.413131718Z",
    "ExecTimeNS": 2199244,
    "OutFiles": {
        "sum": "atcounts.txt.sum"
    },
    "Upstream": {
        "atcounts.txt": {
            "ID": "1judd0hg3oo5j4nburlu",
            "ProcessName": "",
            "Command": "",
            "Params": {},
            "Tags": {},
            "StartTime": "0001-01-01T00:00:00Z",
            "FinishTime": "0001-01-01T00:00:00Z",
            "ExecTimeNS": -1,
            "OutFiles": {},
            "Upstream": {}
        }
    }
}