{
    "ID": "gtr2dbdvzbsa5lzvyfqj",
    "ProcessName": "atcount2",
    "Command": "sed -n 1,$(cat ../count2.txt)p /home/ubuntu/projects/causality-fbp/scipipe-demo/dna_segment_2 | fold -w 1 | grep '[AT]' | wc -l | awk '{ print $1 }' \u003e chry.fa.atcnt2",
    "Params": {},
    "Tags": {},
    "StartTime": "2023-03-13T02:22:13.011444723Z",
    "FinishTime": "2023-03-13T02:22:13.015515759Z",
    "ExecTimeNS": 4071036,
    "OutFiles": {
        "atcount": "chry.fa.atcnt2"
    },
    "Upstream": {
        "count2.txt": {
            "ID": "27ruw9u5az2u54b1khaq",
            "ProcessName": "count2",
            "Command": "echo 3 \u003e count2.txt",
            "Params": {},
            "Tags": {},
            "StartTime": "2023-03-13T02:22:13.009958345Z",
            "FinishTime": "2023-03-13T02:22:13.010974929Z",
            "ExecTimeNS": 1016584,
            "OutFiles": {
                "count": "count2.txt"
            },
            "Upstream": {}
        }
    }
}