{
    "ID": "gcvpz6irutfe4g4cb680",
    "ProcessName": "gcratio",
    "Command": "gc=$(cat ../gccounts.txt.sum); at=$(cat ../atcounts.txt.sum); calc \"$gc/($gc+$at)\" \u003e gcratio.txt",
    "Params": {},
    "Tags": {},
    "StartTime": "2023-02-25T12:57:34.504483468Z",
    "FinishTime": "2023-02-25T12:57:34.507491883Z",
    "ExecTimeNS": 3008415,
    "OutFiles": {
        "gcratio": "gcratio.txt"
    },
    "Upstream": {
        "atcounts.txt.sum": {
            "ID": "wo7aevz0d8q5f8pk8jlu",
            "ProcessName": "atsum",
            "Command": "awk '{ SUM += $1 } END { print SUM }' ../atcounts.txt \u003e atcounts.txt.sum",
            "Params": {},
            "Tags": {},
            "StartTime": "2023-02-25T12:57:34.501394394Z",
            "FinishTime": "2023-02-25T12:57:34.504078384Z",
            "ExecTimeNS": 2683990,
            "OutFiles": {
                "sum": "atcounts.txt.sum"
            },
            "Upstream": {
                "atcounts.txt": {
                    "ID": "fe1rz48hvg26exyh2yj9",
                    "ProcessName": "",
                    "Command": "",
                    "Params": {},
                    "Tags": {},
                    "StartTime": "0001-01-01T00:00:00Z",
                    "FinishTime": "0001-01-01T00:00:00Z",
                    "ExecTimeNS": -1,
                    "OutFiles": {},
                    "Upstream": {}
                }
            }
        },
        "gccounts.txt.sum": {
            "ID": "5sxi7xinftcq3y2n0dur",
            "ProcessName": "gcsum",
            "Command": "awk '{ SUM += $1 } END { print SUM }' ../gccounts.txt \u003e gccounts.txt.sum",
            "Params": {},
            "Tags": {},
            "StartTime": "2023-02-25T12:57:34.501660108Z",
            "FinishTime": "2023-02-25T12:57:34.503972788Z",
            "ExecTimeNS": 2312670,
            "OutFiles": {
                "sum": "gccounts.txt.sum"
            },
            "Upstream": {
                "gccounts.txt": {
                    "ID": "wz9mzy4w8bjpelsx1c5z",
                    "ProcessName": "",
                    "Command": "",
                    "Params": {},
                    "Tags": {},
                    "StartTime": "0001-01-01T00:00:00Z",
                    "FinishTime": "0001-01-01T00:00:00Z",
                    "ExecTimeNS": -1,
                    "OutFiles": {},
                    "Upstream": {}
                }
            }
        }
    }
}