{
    "ID": "54hfcpp87yvmi3tt8kr6",
    "ProcessName": "gcsum",
    "Command": "awk '{ SUM += $1 } END { print SUM }' ../gccounts.txt \u003e gccounts.txt.sum",
    "Params": {},
    "Tags": {},
    "StartTime": "2023-03-13T02:27:14.215872097Z",
    "FinishTime": "2023-03-13T02:27:14.21891719Z",
    "ExecTimeNS": 3045104,
    "OutFiles": {
        "sum": "gccounts.txt.sum"
    },
    "Upstream": {
        "gccounts.txt": {
            "ID": "2lksn47fm4fvux3b4bha",
            "ProcessName": "",
            "Command": "",
            "Params": {},
            "Tags": {},
            "StartTime": "0001-01-01T00:00:00Z",
            "FinishTime": "0001-01-01T00:00:00Z",
            "ExecTimeNS": -1,
            "OutFiles": {},
            "Upstream": {}
        }
    }
}