{
    "ID": "ovvy4hqzp6rtktk1a4ld",
    "ProcessName": "gccount2",
    "Command": "sed -n 1,$(cat ../count2.txt)p /home/ubuntu/projects/causality-fbp/scipipe-demo/dna_segment_2 | fold -w 1 | grep '[GC]' | wc -l | awk '{ print $1 }' \u003e chry.fa.gccnt2",
    "Params": {},
    "Tags": {},
    "StartTime": "2023-03-13T02:25:10.557008052Z",
    "FinishTime": "2023-03-13T02:25:10.562519073Z",
    "ExecTimeNS": 5511011,
    "OutFiles": {
        "gccount": "chry.fa.gccnt2"
    },
    "Upstream": {
        "count2.txt": {
            "ID": "0e196b6lnc00tcso7ruq",
            "ProcessName": "count2",
            "Command": "echo 64 \u003e count2.txt",
            "Params": {},
            "Tags": {},
            "StartTime": "2023-03-13T02:25:10.554648052Z",
            "FinishTime": "2023-03-13T02:25:10.556247255Z",
            "ExecTimeNS": 1599203,
            "OutFiles": {
                "count": "count2.txt"
            },
            "Upstream": {}
        }
    }
}