{
    "ID": "0foqmww1qla01uph87pa",
    "ProcessName": "atcount2",
    "Command": "sed -n 1,$(cat ../count2.txt)p /home/ubuntu/projects/causality-fbp/scipipe-demo/dna_segment_2 | fold -w 1 | grep '[AT]' | wc -l | awk '{ print $1 }' \u003e chry.fa.atcnt2",
    "Params": {},
    "Tags": {},
    "StartTime": "2023-03-13T02:25:59.121595529Z",
    "FinishTime": "2023-03-13T02:25:59.125046755Z",
    "ExecTimeNS": 3451236,
    "OutFiles": {
        "atcount": "chry.fa.atcnt2"
    },
    "Upstream": {
        "count2.txt": {
            "ID": "z3ad94dn158n4xejevjj",
            "ProcessName": "count2",
            "Command": "echo 34 \u003e count2.txt",
            "Params": {},
            "Tags": {},
            "StartTime": "2023-03-13T02:25:59.120392645Z",
            "FinishTime": "2023-03-13T02:25:59.121190208Z",
            "ExecTimeNS": 797553,
            "OutFiles": {
                "count": "count2.txt"
            },
            "Upstream": {}
        }
    }
}