{
    "ID": "y864bhesdg7jnzq8oep2",
    "ProcessName": "gccount2",
    "Command": "sed -n 1,$(cat ../count2.txt)p /home/ubuntu/projects/causality-fbp/scipipe-demo/dna_segment_2 | fold -w 1 | grep '[GC]' | wc -l | awk '{ print $1 }' \u003e chry.fa.gccnt2",
    "Params": {},
    "Tags": {},
    "StartTime": "2023-03-13T02:22:17.79123509Z",
    "FinishTime": "2023-03-13T02:22:17.795296016Z",
    "ExecTimeNS": 4060916,
    "OutFiles": {
        "gccount": "chry.fa.gccnt2"
    },
    "Upstream": {
        "count2.txt": {
            "ID": "5g49xfvdbuq7rtht8jwi",
            "ProcessName": "count2",
            "Command": "echo 4 \u003e count2.txt",
            "Params": {},
            "Tags": {},
            "StartTime": "2023-03-13T02:22:17.789682089Z",
            "FinishTime": "2023-03-13T02:22:17.790750759Z",
            "ExecTimeNS": 1068650,
            "OutFiles": {
                "count": "count2.txt"
            },
            "Upstream": {}
        }
    }
}