{
    "ID": "w0lv9cujxm0wl4r70aev",
    "ProcessName": "atcount1",
    "Command": "sed -n 1,$(cat ../count1.txt)p /home/ubuntu/projects/causality-fbp/scipipe-demo/dna_segment_1 | fold -w 1 | grep '[AT]' | wc -l | awk '{ print $1 }' \u003e chry.fa.atcnt1",
    "Params": {},
    "Tags": {},
    "StartTime": "2023-03-13T02:22:04.58973825Z",
    "FinishTime": "2023-03-13T02:22:04.593452567Z",
    "ExecTimeNS": 3714327,
    "OutFiles": {
        "atcount": "chry.fa.atcnt1"
    },
    "Upstream": {
        "count1.txt": {
            "ID": "z6k8kgphz1ir1fs041no",
            "ProcessName": "count1",
            "Command": "echo 44 \u003e count1.txt",
            "Params": {},
            "Tags": {},
            "StartTime": "2023-03-13T02:22:04.58832982Z",
            "FinishTime": "2023-03-13T02:22:04.589350593Z",
            "ExecTimeNS": 1020783,
            "OutFiles": {
                "count": "count1.txt"
            },
            "Upstream": {}
        }
    }
}