{
    "ID": "tjkkfk7q97wps76yn790",
    "ProcessName": "gcratio",
    "Command": "gc=$(cat ../gccounts.txt.sum); at=$(cat ../atcounts.txt.sum); calc \"$gc/($gc+$at)\" \u003e gcratio.txt",
    "Params": {},
    "Tags": {},
    "StartTime": "2023-02-25T13:01:08.789446896Z",
    "FinishTime": "2023-02-25T13:01:08.792592576Z",
    "ExecTimeNS": 3145670,
    "OutFiles": {
        "gcratio": "gcratio.txt"
    },
    "Upstream": {
        "atcounts.txt.sum": {
            "ID": "a1cuiy1gns0kgffvtq2m",
            "ProcessName": "atsum",
            "Command": "awk '{ SUM += $1 } END { print SUM }' ../atcounts.txt \u003e atcounts.txt.sum",
            "Params": {},
            "Tags": {},
            "StartTime": "2023-02-25T13:01:08.78545793Z",
            "FinishTime": "2023-02-25T13:01:08.787889419Z",
            "ExecTimeNS": 2431489,
            "OutFiles": {
                "sum": "atcounts.txt.sum"
            },
            "Upstream": {
                "atcounts.txt": {
                    "ID": "u2u38pfobp7f7qxx8st0",
                    "ProcessName": "",
                    "Command": "",
                    "Params": {},
                    "Tags": {},
                    "StartTime": "0001-01-01T00:00:00Z",
                    "FinishTime": "0001-01-01T00:00:00Z",
                    "ExecTimeNS": -1,
                    "OutFiles": {},
                    "Upstream": {}
                }
            }
        },
        "gccounts.txt.sum": {
            "ID": "van9ewyd9myn9h20wcqc",
            "ProcessName": "gcsum",
            "Command": "awk '{ SUM += $1 } END { print SUM }' ../gccounts.txt \u003e gccounts.txt.sum",
            "Params": {},
            "Tags": {},
            "StartTime": "2023-02-25T13:01:08.786806083Z",
            "FinishTime": "2023-02-25T13:01:08.788849953Z",
            "ExecTimeNS": 2043860,
            "OutFiles": {
                "sum": "gccounts.txt.sum"
            },
            "Upstream": {
                "gccounts.txt": {
                    "ID": "hrqzn2hi1mp59xpps7uq",
                    "ProcessName": "",
                    "Command": "",
                    "Params": {},
                    "Tags": {},
                    "StartTime": "0001-01-01T00:00:00Z",
                    "FinishTime": "0001-01-01T00:00:00Z",
                    "ExecTimeNS": -1,
                    "OutFiles": {},
                    "Upstream": {}
                }
            }
        }
    }
}