{
    "ID": "g6fq465g4u31bn6trjyn",
    "ProcessName": "atsum",
    "Command": "awk '{ SUM += $1 } END { print SUM }' ../atcounts.txt \u003e atcounts.txt.sum",
    "Params": {},
    "Tags": {},
    "StartTime": "2023-03-13T02:24:51.256046031Z",
    "FinishTime": "2023-03-13T02:24:51.258324144Z",
    "ExecTimeNS": 2278123,
    "OutFiles": {
        "sum": "atcounts.txt.sum"
    },
    "Upstream": {
        "atcounts.txt": {
            "ID": "bl64t5iqbonef4gq8qdg",
            "ProcessName": "",
            "Command": "",
            "Params": {},
            "Tags": {},
            "StartTime": "0001-01-01T00:00:00Z",
            "FinishTime": "0001-01-01T00:00:00Z",
            "ExecTimeNS": -1,
            "OutFiles": {},
            "Upstream": {}
        }
    }
}