{
    "ID": "49c4vdvcje0tsho7ho5i",
    "ProcessName": "gccount1",
    "Command": "sed -n 1,$(cat ../count1.txt)p /home/ubuntu/projects/causality-fbp/scipipe-demo/dna_segment_1 | fold -w 1 | grep '[GC]' | wc -l | awk '{ print $1 }' \u003e chry.fa.gccnt1",
    "Params": {},
    "Tags": {},
    "StartTime": "2023-03-13T02:26:07.327869654Z",
    "FinishTime": "2023-03-13T02:26:07.331745298Z",
    "ExecTimeNS": 3875644,
    "OutFiles": {
        "gccount": "chry.fa.gccnt1"
    },
    "Upstream": {
        "count1.txt": {
            "ID": "onds0jef09iob8nq2hq4",
            "ProcessName": "count1",
            "Command": "echo 87 \u003e count1.txt",
            "Params": {},
            "Tags": {},
            "StartTime": "2023-03-13T02:26:07.325552416Z",
            "FinishTime": "2023-03-13T02:26:07.327269052Z",
            "ExecTimeNS": 1716626,
            "OutFiles": {
                "count": "count1.txt"
            },
            "Upstream": {}
        }
    }
}