{
    "ID": "07ab29uiduz0xfg8071h",
    "ProcessName": "atsum",
    "Command": "awk '{ SUM += $1 } END { print SUM }' ../atcounts.txt \u003e atcounts.txt.sum",
    "Params": {},
    "Tags": {},
    "StartTime": "2023-02-25T13:01:19.301456115Z",
    "FinishTime": "2023-02-25T13:01:19.303226856Z",
    "ExecTimeNS": 1770731,
    "OutFiles": {
        "sum": "atcounts.txt.sum"
    },
    "Upstream": {
        "atcounts.txt": {
            "ID": "ctq74ghveepenyrj98gi",
            "ProcessName": "",
            "Command": "",
            "Params": {},
            "Tags": {},
            "StartTime": "0001-01-01T00:00:00Z",
            "FinishTime": "0001-01-01T00:00:00Z",
            "ExecTimeNS": -1,
            "OutFiles": {},
            "Upstream": {}
        }
    }
}